{
  "as_number": "12338",
  "geolocation": [
    "ES"
  ],
  "lat": "43.0332316704935",
  "lon": "-2.48583259236885",
  "connections": [
    "174",
    "3356",
    "6453",
    "15704",
    "12946",
    "43885",
    "212536",
    "12319",
    "15711",
    "15915",
    "21364",
    "31082",
    "44233",
    "48187",
    "50335",
    "207060",
    "35700",
    "56732",
    "12334",
    "60068",
    "8220",
    "49544"
  ],
  "privacy": [
    1,
    2,
    3,
    5,
    6,
    7,
    8,
    9,
    10,
    12,
    13,
    14,
    15,
    16,
    17,
    18,
    19,
    20,
    21,
    22,
    23,
    24,
    25,
    26,
    27,
    28,
    29,
    30
  ],
  "security": [
    1,
    2,
    3,
    4,
    5,
    7,
    8,
    9,
    11,
    12,
    13,
    14,
    15,
    16,
    17,
    18,
    19,
    20,
    21,
    22,
    23,
    24,
    25,
    26,
    27,
    28,
    29,
    30
  ]
}