{
  "as_number": "6855",
  "geolocation": [
    "SK"
  ],
  "lat": "48.5954837515992",
  "lon": "18.5539988124783",
  "connections": [
    "1299",
    "3320",
    "39904",
    "198101",
    "59747",
    "5588",
    "44234",
    "197694",
    "21433",
    "48417",
    "31127",
    "30929",
    "202877",
    "57007",
    "10780",
    "50698",
    "205080",
    "28892",
    "31349",
    "50695",
    "56344",
    "58239",
    "201163",
    "203165",
    "48451",
    "204394",
    "48298",
    "2571",
    "29298",
    "57760",
    "49044",
    "201603",
    "43757",
    "50881",
    "197083",
    "198282",
    "12344",
    "15380",
    "20708",
    "21942",
    "30898",
    "34443",
    "34521",
    "42826",
    "47749",
    "48304",
    "48405",
    "49275",
    "56891",
    "56973",
    "60086",
    "196861",
    "198103",
    "198143",
    "198494",
    "200355",
    "200828",
    "201841",
    "202564",
    "202830",
    "203080",
    "203122",
    "203411",
    "206198",
    "207095",
    "208329",
    "211731",
    "212325",
    "212537",
    "213057",
    "12767",
    "13036",
    "25093",
    "29148",
    "34462",
    "35096",
    "48574",
    "48907",
    "49117",
    "54189",
    "56955",
    "57788",
    "197642",
    "200222",
    "201447",
    "201997",
    "202073",
    "202084",
    "202876",
    "203208",
    "204690",
    "204716",
    "206909",
    "207696",
    "210117",
    "213247",
    "33891",
    "48689",
    "198543",
    "2607",
    "47232",
    "6939",
    "44185",
    "15935"
  ],
  "privacy": [
    1,
    2,
    3,
    4,
    5,
    6,
    7,
    8,
    9,
    10,
    11,
    12,
    13,
    14,
    15,
    16,
    17,
    18,
    19,
    20,
    21,
    22,
    23,
    24,
    25,
    26,
    27,
    28,
    29,
    30
  ],
  "security": [
    1,
    2,
    3,
    4,
    5,
    6,
    7,
    8,
    9,
    10,
    11,
    12,
    13,
    14,
    15,
    16,
    17,
    18,
    19,
    20,
    21,
    22,
    23,
    24,
    25,
    26,
    27,
    28,
    29,
    30
  ]
}