{
  "as_number": "135420",
  "geolocation": [
    "BD"
  ],
  "lat": "23.6975022515411",
  "lon": "90.4200066836505",
  "connections": [
    "58717",
    "58715",
    "17494",
    "17806"
  ],
  "privacy": [
    1,
    2,
    3,
    4,
    6,
    7,
    8,
    9,
    10,
    11,
    12,
    13,
    14,
    16,
    17,
    18,
    19,
    23,
    24,
    25,
    26,
    27,
    28,
    30
  ],
  "security": [
    1,
    2,
    3,
    4,
    6,
    7,
    8,
    9,
    11,
    12,
    13,
    14,
    15,
    16,
    18,
    19,
    20,
    21,
    23,
    24,
    25,
    26,
    27,
    30
  ]
}