{
  "as_number": "393931",
  "geolocation": [
    "US"
  ],
  "lat": "36.1450001038395",
  "lon": "-86.7950009549865",
  "connections": [
    "3356",
    "7018"
  ],
  "privacy": [
    1,
    2,
    3,
    4,
    5,
    6,
    8,
    9,
    11,
    12,
    14,
    15,
    16,
    19,
    21,
    22,
    25,
    26,
    29,
    30
  ],
  "security": [
    1,
    4,
    6,
    7,
    9,
    10,
    11,
    15,
    16,
    17,
    18,
    19,
    20,
    21,
    23,
    24,
    25,
    26,
    27,
    28
  ]
}