{
  "as_number": "38084",
  "geolocation": [
    "AU"
  ],
  "lat": "-34.031461315548",
  "lon": "151.584053189269",
  "connections": [
    "4826",
    "7545",
    "23655",
    "64073",
    "4764",
    "49544",
    "137409",
    "24516",
    "58511",
    "136557",
    "7575",
    "1828",
    "38880",
    "9268"
  ],
  "privacy": [
    1,
    2,
    3,
    5,
    6,
    7,
    8,
    9,
    10,
    11,
    12,
    13,
    14,
    15,
    16,
    17,
    18,
    19,
    20,
    21,
    22,
    23,
    24,
    25,
    27,
    28,
    29
  ],
  "security": [
    1,
    2,
    3,
    4,
    6,
    7,
    9,
    10,
    11,
    12,
    13,
    14,
    15,
    16,
    17,
    18,
    19,
    21,
    22,
    23,
    24,
    25,
    26,
    27,
    28,
    29,
    30
  ]
}