{
  "as_number": "397086",
  "geolocation": [
    "US"
  ],
  "lat": "45.9910224968987",
  "lon": "-107.333647833623",
  "connections": [
    "6461",
    "1299"
  ],
  "privacy": [
    1,
    4,
    5,
    6,
    7,
    8,
    9,
    11,
    12,
    13,
    16,
    18,
    19,
    21,
    23,
    24,
    25,
    26,
    28,
    30
  ],
  "security": [
    2,
    3,
    5,
    6,
    7,
    9,
    10,
    12,
    13,
    14,
    15,
    17,
    18,
    19,
    20,
    21,
    24,
    26,
    27,
    29
  ]
}