{
  "as_number": "202257",
  "geolocation": [
    "PL"
  ],
  "lat": "49.7990633646805",
  "lon": "21.39406821911",
  "connections": [
    "62081",
    "52195",
    "201053",
    "201054"
  ],
  "features": [
    1,
    2,
    3,
    4,
    5,
    6,
    7,
    8,
    9,
    10,
    11,
    12,
    13,
    14,
    15,
    16,
    17,
    18,
    19,
    20,
    23,
    24,
    25,
    26,
    27,
    28,
    29,
    30,
    31,
    32,
    33,
    35,
    36,
    37,
    38,
    39,
    40,
    41,
    42,
    44,
    46,
    47,
    49,
    50
  ]
}