{
  "as_number": "206530",
  "geolocation": [
    "GB"
  ],
  "lat": "51.64",
  "lon": "-3.33",
  "connections": [
    "1299",
    "1239",
    "60610",
    "37721",
    "50629",
    "50300",
    "45352",
    "41811",
    "398465",
    "62167",
    "58057",
    "5713",
    "13237",
    "6939",
    "9145",
    "49544",
    "31742",
    "34549",
    "13760",
    "25091",
    "50877",
    "8896",
    "20764",
    "18106",
    "41327",
    "25160",
    "4455",
    "37662",
    "4657",
    "14061",
    "396998",
    "34288",
    "48362",
    "207841",
    "47787",
    "14537",
    "31500",
    "29075",
    "12552",
    "28716",
    "35598",
    "132337",
    "199524",
    "42473",
    "52320",
    "3216",
    "1828",
    "7575",
    "12969",
    "12779",
    "1103",
    "16552",
    "51185",
    "3170",
    "6233",
    "39351",
    "37100",
    "3214",
    "60501",
    "34177",
    "17639",
    "63927",
    "12859",
    "3741",
    "47957",
    "41805",
    "36351",
    "14630",
    "39120",
    "15830",
    "37239",
    "16347",
    "24482",
    "9044",
    "39122",
    "35280",
    "6894",
    "34927",
    "33891",
    "1031"
  ],
  "features": [
    1,
    2,
    3,
    4,
    5,
    6,
    7,
    8,
    9,
    10,
    11,
    12,
    13,
    14,
    15,
    16,
    17,
    18,
    19,
    20,
    21,
    22,
    23,
    24,
    25,
    26,
    27,
    28,
    29,
    30
  ]
}