{
  "as_number": "268172",
  "geolocation": [
    "BR"
  ],
  "lat": "-23.69",
  "lon": "-46.56",
  "connections": [
    "266409",
    "263626",
    "37721",
    "14840",
    "57695",
    "263152",
    "51185",
    "271253",
    "47787",
    "39120",
    "263508",
    "1828",
    "52814",
    "52873",
    "52863",
    "24482",
    "6939",
    "23106",
    "28186",
    "263237",
    "35280",
    "53070",
    "61595",
    "42473",
    "28634",
    "264479",
    "267613"
  ],
  "features": [
    1,
    2,
    3,
    4,
    5,
    8,
    9,
    10,
    11,
    12,
    13,
    14,
    15,
    16,
    17,
    18,
    19,
    20,
    21,
    22,
    23,
    24,
    25,
    26,
    27,
    28,
    29,
    30
  ]
}