{
  "as_number": "205185",
  "geolocation": [
    "NL"
  ],
  "lat": "51.8870537775156",
  "lon": "5.34224659195864",
  "connections": [
    "29396",
    "196755",
    "197949",
    "198692",
    "57626",
    "62353",
    "205024",
    "206348",
    "209383",
    "210545",
    "212202",
    "212773",
    "58075"
  ],
  "features": [
    1,
    2,
    3,
    4,
    5,
    6,
    7,
    8,
    9,
    10,
    11,
    12,
    13,
    14,
    15,
    16,
    17,
    18,
    19,
    20,
    21,
    22,
    23,
    24,
    25,
    26,
    27,
    28,
    29,
    30,
    31,
    32,
    33,
    34,
    35,
    36,
    37,
    38,
    39,
    40,
    41,
    42,
    43,
    44,
    45,
    47,
    48,
    49,
    50
  ]
}