{
  "as_number": "35745",
  "geolocation": [
    "PL"
  ],
  "lat": "52.616566514661",
  "lon": "15.5089876924565",
  "connections": [
    "3356",
    "6830",
    "35179",
    "42739",
    "51305",
    "198221",
    "198509",
    "199234",
    "49649",
    "62393",
    "205148",
    "271253",
    "6939",
    "13030",
    "41047",
    "49544",
    "35320",
    "61955",
    "264479",
    "212483",
    "39120",
    "51185",
    "24482",
    "60501",
    "264409",
    "61568",
    "49420"
  ],
  "features": [
    1,
    2,
    3,
    5,
    6,
    7,
    8,
    9,
    10,
    11,
    12,
    13,
    14,
    15,
    16,
    17,
    18,
    19,
    20,
    21,
    22,
    23,
    25,
    26,
    27,
    28,
    29,
    30
  ]
}