{
  "as_number": "209102",
  "geolocation": [
    "IT"
  ],
  "lat": "43.3759830313775",
  "lon": "11.1028600283314",
  "connections": [
    "60501",
    "37721",
    "12897",
    "8283",
    "34347",
    "8893",
    "20928",
    "8560",
    "208808",
    "35710",
    "559",
    "60475",
    "205891",
    "6057",
    "38158",
    "263444",
    "21574",
    "8426",
    "202870",
    "262427",
    "23764",
    "21412",
    "56911",
    "57695",
    "14840",
    "12387",
    "133815",
    "62166",
    "26415",
    "7342",
    "15605",
    "3326",
    "22356",
    "264479",
    "24961",
    "58299",
    "203201",
    "12637",
    "20562",
    "12306",
    "28283",
    "23944",
    "48362",
    "34758",
    "1241",
    "8717",
    "34428",
    "35297",
    "47481",
    "207594",
    "38193",
    "45474",
    "48544",
    "198090",
    "8265",
    "203223",
    "202032",
    "12779",
    "63927",
    "8767",
    "43289",
    "49640",
    "5539",
    "268207",
    "3242",
    "41692",
    "213151",
    "208431",
    "33986",
    "37271",
    "137",
    "553",
    "47147",
    "263903",
    "30848",
    "12859",
    "15169",
    "39120",
    "55805"
  ],
  "features": [
    "filtering",
    "anti_spoofing",
    "coordination",
    "routing_information"
  ]
}