{
  "as_number": "10881",
  "geolocation": [
    "BR"
  ],
  "lat": "-25.3593689811786",
  "lon": "-49.6514601919628",
  "connections": [
    "262494",
    "1299",
    "40138",
    "50599",
    "33668",
    "396565",
    "396745",
    "263649",
    "11260",
    "134478",
    "207594",
    "12271",
    "208135",
    "36629",
    "32167",
    "136308",
    "3242",
    "53231",
    "50058"
  ],
  "filtering": "conformant",
  "anti_spoofing": "conformant",
  "coordination": "conformant",
  "routing_information": "conformant"
}