{
  "as_number": "2152",
  "geolocation": [
    "US"
  ],
  "lat": "35.6746354471497",
  "lon": "-119.545299989619",
  "connections": [
    "3356",
    "54048",
    "40498",
    "195",
    "567",
    "6360",
    "46749",
    "395226",
    "2920",
    "7377",
    "23024",
    "6099",
    "6106",
    "3734",
    "21694",
    "55032",
    "11188",
    "11687",
    "63435",
    "16",
    "31",
    "5653",
    "5739",
    "11293",
    "29878",
    "32361",
    "46357",
    "52",
    "131",
    "257",
    "299",
    "5783",
    "6192",
    "17369",
    "21924",
    "22323",
    "31764",
    "32933",
    "46425",
    "46985",
    "393425",
    "394917",
    "396310",
    "25",
    "2037",
    "6492",
    "10294",
    "10867",
    "11159",
    "13940",
    "14212",
    "14255",
    "16573",
    "18558",
    "18975",
    "21545",
    "21708",
    "21828",
    "21915",
    "22063",
    "22226",
    "22315",
    "23065",
    "23117",
    "23309",
    "23323",
    "23369",
    "23483",
    "23489",
    "25664",
    "26066",
    "26403",
    "26492",
    "27502",
    "30193",
    "30679",
    "46290",
    "54179",
    "54192",
    "393282",
    "394435",
    "396465",
    "399574",
    "7960",
    "396450",
    "11164",
    "46750",
    "9",
    "3701"
  ],
  "features": [
    1,
    2,
    3,
    4,
    5,
    6,
    7,
    8,
    9,
    10,
    11,
    12,
    13,
    14,
    15,
    16,
    17,
    18,
    19,
    20,
    21,
    22,
    23,
    24,
    25,
    26,
    27,
    28,
    29,
    30
  ]
}