{
  "as_number": "203329",
  "geolocation": [
    "DE"
  ],
  "lat": "48.7873693594817",
  "lon": "10.6196018340981",
  "connections": [
    "1299",
    "2914",
    "3320",
    "8220",
    "13237",
    "25291",
    "208025",
    "29205",
    "50246",
    "62075",
    "15605"
  ],
  "features": [
    1,
    2,
    3,
    4,
    5,
    6,
    7,
    8,
    9,
    10,
    11,
    12,
    13,
    14,
    15,
    16,
    17,
    18,
    19,
    20,
    21,
    22,
    23,
    24,
    25,
    27,
    28,
    29,
    30
  ]
}