{
  "as_number": "262517",
  "geolocation": [
    "BR"
  ],
  "lat": "-14.4606716726443",
  "lon": "-48.7241534119182",
  "connections": [
    "28329",
    "61832",
    "267613",
    "263558",
    "262579",
    "264368",
    "265314",
    "267940",
    "270662",
    "268048",
    "269320",
    "269516",
    "272266",
    "266025",
    "270242",
    "52708"
  ],
  "features": [
    1,
    2,
    3,
    4,
    5,
    6,
    7,
    8,
    9,
    10,
    11,
    12,
    13,
    14,
    15,
    16,
    17,
    18,
    19,
    20,
    21,
    22,
    23,
    24,
    25,
    26,
    27,
    28,
    29,
    30
  ]
}