{
  "as_number": "50581",
  "geolocation": [
    "UA"
  ],
  "lat": "49.517454172314",
  "lon": "32.1455730744252",
  "connections": [
    "174",
    "1299",
    "2914",
    "6939",
    "9002",
    "31500",
    "28917",
    "24785",
    "199995",
    "25082",
    "51993",
    "51528",
    "39431",
    "196777",
    "49588",
    "56386",
    "24872",
    "203394",
    "52180",
    "198030",
    "57197",
    "15461",
    "51742",
    "199785",
    "12662",
    "39762",
    "196863",
    "205318",
    "16327",
    "48045",
    "48411",
    "207422",
    "31149",
    "31388",
    "35737",
    "41737",
    "42441",
    "43786",
    "47245",
    "49889",
    "50027",
    "51848",
    "56525",
    "57993",
    "197125",
    "197144",
    "197554",
    "203531",
    "35320",
    "20562",
    "16265"
  ],
  "features": [
    1,
    2,
    3,
    4,
    5,
    6,
    7,
    8,
    9,
    10,
    11,
    12,
    13,
    14,
    15,
    16,
    17,
    18,
    19,
    20,
    21,
    22,
    23,
    24,
    25,
    26,
    27,
    28,
    29,
    30
  ]
}