{
  "as_number": "58314",
  "geolocation": [
    "RU"
  ],
  "lat": "44.9069435425459",
  "lon": "39.1051004582128",
  "connections": [
    "9002",
    "3216",
    "20485",
    "31133",
    "200442",
    "34777",
    "198645",
    "57323",
    "199583",
    "34855",
    "201267"
  ],
  "features": [
    1,
    2,
    3,
    4,
    6,
    7,
    8,
    9,
    10,
    11,
    12,
    13,
    14,
    15,
    16,
    17,
    18,
    19,
    20,
    21,
    22,
    23,
    24,
    25,
    26,
    27,
    28,
    29,
    30
  ]
}