{
  "as_number": "29446",
  "geolocation": [
    "GB"
  ],
  "lat": "51.6789136665956",
  "lon": "0.0596572452129479",
  "connections": [
    "174",
    "3257",
    "8276",
    "37721",
    "62167",
    "271253",
    "6939",
    "41047",
    "31742",
    "3741",
    "35266",
    "286",
    "9044",
    "264479",
    "212483",
    "1828",
    "12552",
    "60501",
    "14061",
    "199524",
    "6894",
    "61568",
    "42473",
    "36351",
    "7575",
    "15830",
    "39120",
    "51185",
    "24482",
    "28716",
    "4455"
  ],
  "features": [
    1,
    2,
    3,
    4,
    5,
    6,
    7,
    8,
    9,
    10,
    11,
    12,
    13,
    14,
    15,
    16,
    17,
    18,
    20,
    21,
    22,
    23,
    24,
    25,
    26,
    27,
    28,
    29,
    30
  ]
}