{
  "as_number": "42678",
  "geolocation": [
    "RU"
  ],
  "lat": "55.8234906227102",
  "lon": "37.6020278180392",
  "connections": [
    "20485",
    "35598",
    "8732",
    "8595",
    "14907",
    "49673",
    "49544",
    "14061",
    "15830",
    "18106",
    "3303",
    "199524",
    "36351",
    "41327"
  ],
  "features": [
    1,
    4,
    5,
    6,
    7,
    8,
    9,
    10,
    11,
    12,
    13,
    14,
    15,
    16,
    17,
    18,
    19,
    20,
    21,
    22,
    23,
    24,
    25,
    27,
    28,
    29,
    30
  ]
}