{
  "as_number": "54535",
  "geolocation": [
    "US"
  ],
  "lat": "45.3729808008164",
  "lon": "-120.936269754938",
  "connections": [
    "174",
    "6461",
    "1299",
    "3257",
    "701",
    "6453",
    "15830",
    "3549",
    "12200",
    "4713",
    "5488",
    "286",
    "20055"
  ],
  "features": [
    2,
    3,
    4,
    5,
    6,
    7,
    8,
    9,
    10,
    11,
    12,
    13,
    14,
    15,
    17,
    19,
    20,
    21,
    22,
    23,
    24,
    25,
    26,
    27,
    28,
    29,
    30
  ]
}