{
  "as_number": "266135",
  "geolocation": [
    "BR"
  ],
  "lat": "-19.9287524752269",
  "lon": "-44.0187493809",
  "connections": [
    "37468",
    "21574",
    "267076",
    "266062",
    "262805",
    "52809",
    "37721",
    "61595",
    "53070",
    "267613",
    "37497",
    "52814",
    "7195",
    "263152",
    "51185",
    "57695",
    "1828",
    "61568",
    "264479",
    "28634",
    "42473",
    "23106",
    "6939",
    "35280",
    "28186",
    "263237",
    "52873",
    "52863",
    "24482",
    "39120",
    "263508",
    "47787",
    "271253"
  ],
  "features": [
    1,
    2,
    3,
    4,
    5,
    6,
    7,
    8,
    9,
    10,
    11,
    12,
    13,
    14,
    15,
    16,
    17,
    18,
    19,
    20,
    21,
    22,
    23,
    24,
    25,
    26,
    27,
    29,
    30
  ]
}