{
  "as_number": "264993",
  "geolocation": [
    "BR"
  ],
  "lat": "-12.42",
  "lon": "-38.33",
  "connections": [
    "52872",
    "268089",
    "37721",
    "271253",
    "267613",
    "263237",
    "57695",
    "263508",
    "1828",
    "7195",
    "263152",
    "47787",
    "51185",
    "39120",
    "52863",
    "24482",
    "52814",
    "37497",
    "28186",
    "23106",
    "28634",
    "264479",
    "42473",
    "61568",
    "53070",
    "61595"
  ],
  "features": [
    1,
    2,
    3,
    4,
    6,
    7,
    8,
    9,
    10,
    11,
    12,
    14,
    15,
    16,
    17,
    18,
    19,
    20,
    21,
    22,
    23,
    24,
    25,
    26,
    27,
    28,
    29,
    30
  ]
}