{
  "as_number": "35012",
  "geolocation": [
    "FR"
  ],
  "lat": "50.2693405866081",
  "lon": "2.99468493643182",
  "connections": [
    "174",
    "8218",
    "15557",
    "271253",
    "50628",
    "6939",
    "59689",
    "29467",
    "41047",
    "49544",
    "25091",
    "35426",
    "47957",
    "20766",
    "34224",
    "6774",
    "29075",
    "264479",
    "212483",
    "1828",
    "34019",
    "41327",
    "15547",
    "39120",
    "16347",
    "14537",
    "24482",
    "35280",
    "6696",
    "61568",
    "264409",
    "51185",
    "35600",
    "4455",
    "60501",
    "34177"
  ],
  "features": [
    1,
    2,
    3,
    4,
    5,
    6,
    7,
    8,
    9,
    10,
    11,
    12,
    13,
    14,
    15,
    16,
    18,
    19,
    20,
    21,
    22,
    23,
    24,
    25,
    26,
    27,
    28,
    29,
    30
  ]
}