{
  "as_number": "31608",
  "geolocation": [
    "PL"
  ],
  "lat": "53.8352714689639",
  "lon": "16.316714607595",
  "connections": [
    "12741",
    "20804",
    "34805",
    "197399",
    "197310",
    "24748",
    "271253",
    "6939",
    "264479",
    "212483",
    "49420",
    "51185",
    "60501",
    "12912",
    "39120",
    "61568",
    "264409"
  ],
  "features": [
    1,
    2,
    3,
    4,
    5,
    6,
    7,
    8,
    10,
    11,
    12,
    13,
    14,
    15,
    16,
    17,
    18,
    19,
    21,
    22,
    23,
    24,
    26,
    27,
    28,
    29,
    30
  ]
}