{
  "as_number": "393238",
  "geolocation": [
    "US"
  ],
  "lat": "41.9150661902184",
  "lon": "-91.6179745123662",
  "connections": [
    "174",
    "6939",
    "21896",
    "46552",
    "3410",
    "23538",
    "36719",
    "393308",
    "397051",
    "397185",
    "397741",
    "397833",
    "27304",
    "399860",
    "14230"
  ],
  "features": [
    1,
    2,
    3,
    4,
    5,
    6,
    7,
    8,
    9,
    10,
    11,
    12,
    13,
    14,
    15,
    16,
    17,
    18,
    19,
    20,
    21,
    22,
    23,
    24,
    25,
    26,
    27,
    28,
    29,
    30
  ]
}