{
  "as_number": "199624",
  "geolocation": [
    "RU"
  ],
  "lat": "55.778241681912",
  "lon": "37.6218079173754",
  "connections": [
    "31500",
    "50509",
    "35598",
    "8641",
    "198185",
    "44772",
    "197632",
    "199623",
    "48477",
    "57867",
    "49929",
    "202150",
    "47857",
    "49058",
    "56857",
    "57290",
    "57490",
    "199622",
    "199647",
    "37721",
    "56655",
    "14907",
    "49673",
    "47441",
    "6939",
    "51904",
    "49544",
    "34549",
    "3303",
    "25091",
    "18106",
    "41327",
    "1031",
    "15830",
    "60501",
    "36351",
    "199524",
    "24482",
    "41722",
    "8492",
    "14061",
    "41805"
  ],
  "features": [
    1,
    2,
    3,
    4,
    5,
    6,
    7,
    8,
    10,
    11,
    12,
    13,
    14,
    15,
    16,
    17,
    18,
    19,
    20,
    21,
    22,
    23,
    24,
    25,
    26,
    27,
    28,
    29,
    30
  ]
}