{
  "as_number": "47258",
  "geolocation": [
    "RU"
  ],
  "lat": "55.9084716089141",
  "lon": "37.7723798085294",
  "connections": [
    "20764",
    "31133",
    "35598",
    "48347",
    "50509",
    "29076",
    "5467",
    "14907",
    "49673",
    "47441",
    "6939",
    "18106",
    "8492",
    "36351",
    "3303",
    "199524",
    "49544",
    "14061",
    "41722",
    "41327"
  ],
  "features": [
    1,
    2,
    3,
    5,
    6,
    7,
    8,
    10,
    11,
    12,
    13,
    14,
    15,
    16,
    17,
    18,
    19,
    20,
    21,
    22,
    23,
    24,
    25,
    26,
    28,
    29,
    30
  ]
}