{
  "as_number": "8595",
  "geolocation": [
    "RU"
  ],
  "lat": "55.7723411394071",
  "lon": "37.6822651049421",
  "connections": [
    "9002",
    "3216",
    "35598",
    "28968",
    "12418",
    "43267",
    "29124",
    "31370",
    "60771",
    "42696",
    "202857",
    "208587",
    "34300",
    "42678",
    "47156",
    "49825",
    "50516",
    "57996",
    "200662",
    "206152",
    "41443",
    "50283",
    "51893",
    "57867",
    "61991",
    "200743",
    "203401",
    "209930",
    "33797",
    "33987",
    "35571",
    "44199",
    "48050",
    "50409",
    "50608",
    "50644",
    "50946",
    "57824",
    "62115",
    "197987",
    "199502",
    "204067",
    "204159",
    "204848",
    "210899",
    "28741",
    "30768",
    "35631",
    "43537",
    "43917",
    "44759",
    "50513",
    "50713",
    "51884",
    "56477",
    "57186",
    "58284",
    "60535",
    "203766",
    "204117",
    "204305",
    "211605",
    "20764",
    "14907",
    "49673",
    "49544",
    "3303",
    "18106",
    "36351",
    "15830",
    "41327",
    "14061",
    "199524"
  ],
  "features": [
    1,
    2,
    3,
    4,
    5,
    6,
    7,
    8,
    9,
    10,
    11,
    12,
    13,
    14,
    15,
    16,
    17,
    18,
    19,
    20,
    21,
    22,
    23,
    24,
    25,
    26,
    27,
    28,
    29,
    30
  ]
}