{
  "as_number": "266213",
  "geolocation": [
    "BR"
  ],
  "lat": "-23.971748545961",
  "lon": "-52.5492139298807",
  "connections": [
    "262355",
    "28359",
    "60503",
    "265207",
    "267885",
    "52873",
    "271253",
    "52814",
    "37497",
    "52863",
    "24482",
    "263152",
    "57695",
    "47787",
    "263508",
    "39120",
    "1828",
    "53070",
    "61595",
    "264479",
    "28634",
    "42473",
    "267613",
    "28186",
    "35280"
  ],
  "features": [
    1,
    2,
    3,
    4,
    5,
    6,
    7,
    8,
    9,
    10,
    11,
    12,
    13,
    14,
    15,
    16,
    17,
    18,
    20,
    21,
    22,
    23,
    25,
    26,
    27,
    28,
    29,
    30
  ]
}