{
  "as_number": "19754",
  "geolocation": [
    "US"
  ],
  "lat": "35.1142233665293",
  "lon": "-95.193832706514",
  "connections": [
    "1299",
    "13428",
    "32709",
    "27216",
    "27027",
    "53423",
    "63296",
    "11046",
    "13823",
    "10689",
    "33218",
    "54932",
    "394883",
    "14382",
    "32624",
    "35862",
    "397952",
    "13337",
    "16822",
    "17004",
    "18435",
    "29706",
    "30182",
    "54938",
    "62482",
    "62948",
    "64281",
    "394541",
    "397026",
    "400605",
    "11471",
    "11821",
    "14984",
    "19032",
    "26449",
    "27192",
    "53289",
    "394153",
    "396107",
    "396953",
    "54527",
    "14907",
    "13786",
    "3130",
    "2044",
    "6939",
    "49544",
    "53828",
    "7713",
    "19653",
    "11272",
    "18106",
    "1828",
    "9002",
    "8220",
    "2603",
    "4181",
    "1798",
    "5645",
    "151062",
    "36351",
    "11686",
    "2381",
    "63927",
    "19151",
    "293",
    "23367",
    "58511",
    "24482",
    "852",
    "4826",
    "34927",
    "35280",
    "7575",
    "29838",
    "46413",
    "394256",
    "397293",
    "137409"
  ],
  "features": [
    1,
    2,
    3,
    4,
    5,
    6,
    7,
    8,
    9,
    10,
    11,
    12,
    13,
    14,
    15,
    16,
    17,
    18,
    19,
    20,
    21,
    22,
    23,
    24,
    25,
    26,
    27,
    28,
    29,
    30
  ]
}