{
  "as_number": "50115",
  "geolocation": [
    "UA"
  ],
  "lat": "46.6835673079469",
  "lon": "30.5855195215933",
  "connections": [
    "35320",
    "35297",
    "201803",
    "41205",
    "211250",
    "50263",
    "59613",
    "37721",
    "271253",
    "51185",
    "8492",
    "39120",
    "34549",
    "41327",
    "39351",
    "212483",
    "24482",
    "47441",
    "48919",
    "34224",
    "49544",
    "6939",
    "25091",
    "14061",
    "35598",
    "60501",
    "56655",
    "1031",
    "264479",
    "49673",
    "61568"
  ],
  "features": [
    1,
    2,
    3,
    4,
    5,
    6,
    7,
    8,
    9,
    10,
    11,
    12,
    13,
    14,
    15,
    16,
    17,
    18,
    19,
    20,
    21,
    22,
    23,
    24,
    26,
    27,
    28,
    29,
    30
  ]
}