{
  "as_number": "59835",
  "geolocation": [
    "SE"
  ],
  "lat": "58.1948870078339",
  "lon": "15.11787679078",
  "connections": [
    "8674",
    "1239",
    "6939",
    "15830",
    "8289",
    "1828",
    "205206",
    "51519",
    "39351",
    "61955",
    "31500",
    "28917",
    "20764",
    "2603",
    "12552",
    "24482",
    "25091",
    "31133",
    "49544",
    "63927",
    "35598",
    "35280",
    "13194",
    "50304",
    "3399",
    "199524",
    "3303",
    "42473"
  ],
  "features": [
    1,
    2,
    3,
    4,
    5,
    6,
    7,
    8,
    9,
    10,
    12,
    13,
    14,
    15,
    16,
    18,
    19,
    20,
    21,
    22,
    23,
    24,
    25,
    26,
    27,
    28,
    29,
    30
  ]
}