{
  "as_number": "61414",
  "geolocation": [
    "GB"
  ],
  "lat": "45.6765321106408",
  "lon": "134.062310128082",
  "connections": [
    "21859",
    "17676",
    "49466",
    "6939",
    "23764",
    "17639",
    "1828",
    "59105",
    "35280",
    "24482",
    "9370",
    "4775"
  ],
  "features": [
    1,
    2,
    3,
    4,
    5,
    6,
    7,
    8,
    9,
    10,
    11,
    12,
    14,
    15,
    16,
    17,
    18,
    20,
    22,
    23,
    24,
    25,
    26,
    27,
    28,
    29,
    30
  ]
}