{
  "as_number": "30038",
  "geolocation": [
    "US"
  ],
  "lat": "40.6793177927971",
  "lon": "-74.0100717111896",
  "connections": [
    "174",
    "6939",
    "19151",
    "37721",
    "50629",
    "271253",
    "13786",
    "49544",
    "34549",
    "37468",
    "1828",
    "396998",
    "41327",
    "36351",
    "22652",
    "14061",
    "35280",
    "199524",
    "24482"
  ],
  "features": [
    1,
    2,
    3,
    4,
    5,
    6,
    7,
    8,
    9,
    10,
    11,
    12,
    13,
    14,
    15,
    16,
    17,
    19,
    20,
    21,
    23,
    24,
    25,
    26,
    27,
    28,
    29,
    30
  ]
}