{
  "as_number": "21271",
  "geolocation": [
    "ML"
  ],
  "lat": "12.6829921111734",
  "lon": "-8.0212454094521",
  "connections": [
    "29571",
    "8346",
    "6713"
  ],
  "privacy": [
    3,
    5,
    6,
    8,
    9,
    10,
    12,
    13,
    14,
    16,
    17,
    18,
    19,
    20,
    21,
    23,
    24,
    25,
    26,
    28,
    29,
    30
  ],
  "security": [
    1,
    2,
    4,
    5,
    6,
    8,
    9,
    10,
    11,
    12,
    13,
    17,
    18,
    19,
    20,
    22,
    23,
    24,
    25,
    28,
    29,
    30
  ]
}