{
  "as_number": "396402",
  "geolocation": [
    "US"
  ],
  "lat": "47.215228137109",
  "lon": "-122.456817054437",
  "connections": [
    "209",
    "33650"
  ],
  "privacy": [
    1,
    2,
    3,
    4,
    5,
    6,
    7,
    8,
    9,
    10,
    12,
    13,
    14,
    17,
    18,
    19,
    23,
    26,
    29,
    30
  ],
  "security": [
    1,
    2,
    3,
    4,
    5,
    8,
    9,
    10,
    12,
    13,
    14,
    15,
    18,
    19,
    21,
    24,
    25,
    26,
    27,
    29
  ]
}