{
  "as_number": "136933",
  "geolocation": [
    "HK"
  ],
  "lat": "26.9346260355383",
  "lon": "112.734266163589",
  "connections": [
    "1299",
    "2914",
    "6939",
    "3223",
    "6134",
    "136970",
    "139471",
    "136907",
    "141159",
    "42960",
    "132325",
    "132698",
    "136746",
    "136778",
    "136950",
    "138630",
    "139635",
    "135056",
    "55518",
    "58453",
    "4608",
    "4637",
    "55720",
    "41095",
    "8359",
    "49544",
    "7713",
    "1239",
    "7660",
    "9304",
    "17639",
    "9002",
    "140627",
    "23673",
    "9930",
    "2603",
    "3491",
    "132337",
    "32558",
    "35280",
    "4826",
    "24482",
    "39120",
    "132825",
    "10358"
  ],
  "privacy": [
    1,
    2,
    4,
    5,
    6,
    7,
    8,
    9,
    10,
    11,
    12,
    13,
    14,
    15,
    16,
    17,
    18,
    19,
    20,
    21,
    22,
    23,
    24,
    25,
    26,
    27,
    28,
    29,
    30
  ],
  "security": [
    1,
    2,
    3,
    4,
    5,
    6,
    7,
    8,
    9,
    10,
    11,
    12,
    13,
    15,
    16,
    17,
    18,
    19,
    20,
    21,
    22,
    23,
    24,
    25,
    26,
    27,
    28,
    29,
    30
  ]
}