{
  "as_number": "12926",
  "geolocation": [
    "PT"
  ],
  "lat": "39.0937792304594",
  "lon": "-9.08158592094472",
  "connections": [
    "174",
    "6939",
    "29119",
    "47784",
    "47787",
    "8220",
    "37468"
  ],
  "privacy": [
    1,
    2,
    3,
    4,
    7,
    9,
    10,
    11,
    12,
    14,
    15,
    16,
    17,
    18,
    19,
    20,
    21,
    22,
    23,
    24,
    25,
    26,
    27,
    28,
    29,
    30
  ],
  "security": [
    1,
    2,
    3,
    4,
    5,
    6,
    8,
    10,
    11,
    12,
    13,
    14,
    15,
    16,
    17,
    18,
    19,
    20,
    22,
    23,
    24,
    25,
    26,
    27,
    28,
    29
  ]
}