{
  "as_number": "64208",
  "geolocation": [
    "US"
  ],
  "lat": "38.9721419145824",
  "lon": "-81.4041168745105",
  "connections": [
    "174",
    "3356",
    "6461",
    "46977",
    "37721",
    "25885",
    "14907",
    "398465",
    "11039",
    "13786",
    "6939",
    "49544",
    "53828",
    "7713",
    "19653",
    "40934",
    "52320",
    "23367",
    "59605",
    "35280",
    "24482",
    "4826",
    "293",
    "2381",
    "9505",
    "36351",
    "16735",
    "14061",
    "8220",
    "58511",
    "7575",
    "1828",
    "57695",
    "16552"
  ],
  "privacy": [
    1,
    2,
    3,
    4,
    6,
    7,
    8,
    9,
    10,
    11,
    12,
    13,
    14,
    15,
    16,
    17,
    18,
    19,
    20,
    21,
    22,
    23,
    24,
    25,
    26,
    27,
    28,
    29,
    30
  ],
  "security": [
    1,
    2,
    3,
    4,
    6,
    7,
    8,
    9,
    10,
    11,
    12,
    13,
    14,
    15,
    16,
    17,
    18,
    19,
    20,
    21,
    22,
    23,
    24,
    25,
    26,
    27,
    28,
    29,
    30
  ]
}