{
  "as_number": "327799",
  "geolocation": [
    "BI"
  ],
  "lat": "-3.36235957943796",
  "lon": "29.3738296478477",
  "connections": [
    "30844",
    "37084",
    "37273",
    "36890",
    "25429"
  ],
  "privacy": [
    1,
    2,
    3,
    4,
    5,
    6,
    7,
    8,
    9,
    10,
    11,
    12,
    14,
    15,
    17,
    18,
    19,
    20,
    21,
    22,
    23,
    24,
    25,
    26,
    29
  ],
  "security": [
    3,
    4,
    5,
    6,
    7,
    8,
    9,
    10,
    11,
    13,
    14,
    15,
    16,
    17,
    18,
    19,
    20,
    21,
    22,
    23,
    24,
    27,
    28,
    29,
    30
  ]
}