{
  "as_number": "49115",
  "geolocation": [
    "SK"
  ],
  "lat": "48.6370049813945",
  "lon": "21.6379292261446",
  "connections": [
    "174",
    "60068",
    "39392",
    "29405",
    "35493",
    "44452",
    "209429",
    "37721",
    "35369",
    "271253",
    "6939",
    "41047",
    "49544",
    "34224",
    "61955",
    "264479",
    "212483",
    "40994",
    "51184",
    "51185",
    "60501",
    "8447",
    "13194",
    "39120",
    "61568",
    "59890",
    "29504",
    "264409"
  ],
  "features": [
    1,
    2,
    3,
    4,
    6,
    7,
    8,
    9,
    10,
    11,
    12,
    13,
    14,
    15,
    16,
    17,
    18,
    19,
    20,
    22,
    23,
    24,
    25,
    26,
    27,
    28,
    29,
    30
  ]
}