{
  "as_number": "19411",
  "geolocation": [
    "CL"
  ],
  "lat": "-30",
  "lon": "-71",
  "connections": [
    "22661",
    "16471",
    "18747"
  ],
  "privacy": [
    1,
    2,
    4,
    5,
    7,
    8,
    10,
    11,
    12,
    14,
    16,
    19,
    20,
    21,
    22,
    23,
    25,
    26,
    28,
    29,
    30
  ],
  "security": [
    1,
    2,
    3,
    5,
    8,
    9,
    10,
    11,
    12,
    13,
    14,
    15,
    16,
    18,
    19,
    20,
    21,
    24,
    26,
    27,
    28
  ]
}