{
  "as_number": "6886",
  "geolocation": [
    "UA"
  ],
  "lat": "48.226117341197",
  "lon": "37.1939110598017",
  "connections": [
    "9002",
    "28917",
    "3326",
    "12883",
    "50927",
    "202198",
    "44673",
    "50649",
    "57659",
    "203781",
    "205048",
    "208194",
    "209952",
    "8647",
    "37721",
    "56655",
    "49673",
    "271253",
    "47441",
    "6939",
    "41047",
    "49544",
    "34549",
    "3303",
    "25091",
    "34224",
    "39351",
    "264479",
    "212483",
    "35598",
    "41327",
    "48919",
    "51185",
    "1031",
    "264409",
    "61568",
    "24724",
    "13194",
    "24482",
    "39120",
    "60501",
    "8492"
  ],
  "features": [
    1,
    2,
    3,
    4,
    5,
    6,
    7,
    8,
    9,
    10,
    11,
    12,
    13,
    15,
    16,
    17,
    18,
    19,
    20,
    21,
    22,
    23,
    24,
    25,
    26,
    27,
    28,
    29,
    30
  ]
}