{
  "as_source": "205550",
  "as_destination": "55260",
  "security": {
    "strict": [
      6,
      9
    ],
    "best_effort": [
      10,
      21,
      23,
      25
    ],
    "best_effort_mode": "biggest_subset"
  },
  "privacy": {
    "strict": [
      2,
      4
    ],
    "best_effort": [
      3,
      15,
      17,
      25
    ],
    "best_effort_mode": "ordered_list"
  },
  "geolocation": {
    "exclude": [
      "BB",
      "CD",
      "EG",
      "GM",
      "KE",
      "LC",
      "PF",
      "PH",
      "PW"
    ]
  },
  "path_optimization": "none",
  "multipath": {
    "target_amount_of_paths": 1,
    "minimum_number_of_paths": 1
  }
}