{
  "as_source": "141741",
  "as_destination": "18113",
  "privacy": {
    "strict": [],
    "best_effort": [
      3,
      4,
      6,
      18,
      20,
      25,
      30
    ],
    "best_effort_mode": "biggest_subset"
  },
  "security": {
    "strict": [],
    "best_effort": [
      6,
      13,
      26
    ],
    "best_effort_mode": "biggest_subset"
  },
  "geolocation": {
    "exclude": [
      "AD",
      "AO",
      "AQ",
      "BZ",
      "GN",
      "IS",
      "MD"
    ]
  },
  "path_optimization": "none",
  "multipath": {
    "target_amount_of_paths": 1,
    "minimum_number_of_paths": 1
  }
}