{
  "as_source": "212195",
  "as_destination": "394057",
  "requirements": {
    "strict": [
      1,
      2,
      8,
      12,
      13,
      17,
      23,
      24,
      25,
      27
    ],
    "best_effort": [
      4,
      6,
      10,
      16,
      18,
      19
    ],
    "best_effort_mode": "biggest_subset"
  },
  "geolocation": {
    "exclude": [
      "CK",
      "CX",
      "LI",
      "MR",
      "SX",
      "SZ"
    ]
  },
  "path_optimization": "minimize_number_of_hops",
  "multipath": {
    "target_amount_of_paths": 4,
    "minimum_number_of_paths": 1
  },
  "fallback_to_ebgp_if_no_path_found": "true"
}